README.md
setup.py
Scripts/s33specimagesum.bat
Scripts/s33specimagesum.sh
s33specimagesum/__init__.py
s33specimagesum/__main__.py
s33specimagesum/mainwindow.py
s33specimagesum/srange.py
s33specimagesum.egg-info/PKG-INFO
s33specimagesum.egg-info/SOURCES.txt
s33specimagesum.egg-info/dependency_links.txt
s33specimagesum.egg-info/requires.txt
s33specimagesum.egg-info/top_level.txt