Metadata-Version: 1.0
Name: s33specimagesum
Version: 1.2.9
Summary: Python Program to sum images in a scan.  This program was writtenfor the case that each image in the scan 
Home-page: UNKNOWN
Author: John Hammonds
Author-email: JPHammonds@anl.gov
License: See LICENSE File
Platform: any
